biofrost/__init__.py
biofrost/env.py
biofrost/logger.py
biofrost/main.py
biofrost/utils.py
biofrost/version.py
biofrost/analysis/__init__.py
biofrost/analysis/bioinfo.py
biofrost/analysis/de.py
biofrost/analysis/models.py
biofrost/analysis/ontology.py
biofrost/analysis/taxonomy.py
biofrost/plot/__init__.py
biofrost/plot/circos.py
biofrost/plot/utils.py
biofrost/sequence/__init__.py
biofrost/sequence/io.py
biofrost/sequence/kmer.py
biofrost-0.1.0.dist-info/LICENSE
biofrost-0.1.0.dist-info/METADATA
biofrost-0.1.0.dist-info/WHEEL
biofrost-0.1.0.dist-info/entry_points.txt
biofrost-0.1.0.dist-info/top_level.txt
biofrost-0.1.0.dist-info/zip-safe
biofrost-0.1.0.dist-info/RECORD
